{"skeleton":{"hash":"Zuwt7ZMqR6k","spine":"4.0.39","x":-51.89,"y":-40.69,"width":96.32,"height":109.37,"images":"","audio":"C:/Users/my/Desktop/용병 추가/bomb man"},"bones":[{"name":"root","x":2.72,"y":5.44},{"name":"bone","parent":"root","length":25.38,"rotation":-91.36,"x":-0.87,"y":-0.93},{"name":"body","parent":"bone","length":23.86,"rotation":1.36,"x":-0.23,"y":-3.13},{"name":"head","parent":"bone","length":19.93,"rotation":-178.64,"x":3.24,"y":2.15},{"name":"shadow","parent":"root","rotation":-92.56,"x":-5.44,"y":-30.46,"color":"9b9b9bca"},{"name":"magic circle","parent":"root","x":-3.86,"y":-26.93},{"name":"leg(right)","parent":"body","length":7.27,"rotation":-4.9,"x":19.15,"y":-7.46},{"name":"leg(left)","parent":"body","length":7.07,"rotation":-5.04,"x":18.95,"y":8.29},{"name":"hand(left)","parent":"body","length":10.65,"rotation":43.45,"x":8.8,"y":9.93},{"name":"hand(right)","parent":"body","length":11.64,"rotation":-36.47,"x":7.58,"y":-8.39}],"slots":[{"name":"shadow","bone":"shadow","attachment":"shadow"},{"name":"magic circle(blue)","bone":"magic circle","attachment":"magic circle(blue)"},{"name":"leg(left)","bone":"leg(left)","attachment":"leg(left)"},{"name":"leg(right)","bone":"leg(right)","attachment":"leg(right)"},{"name":"hand(left)","bone":"hand(left)","attachment":"hand(left)"},{"name":"body","bone":"body","attachment":"body"},{"name":"head","bone":"head","attachment":"head"},{"name":"hand(right)","bone":"hand(right)","attachment":"hand(right)"}],"skins":[{"name":"default","attachments":{"body":{"body":{"x":3.42,"y":-7.56,"rotation":90,"width":50,"height":51}},"hand(left)":{"hand(left)":{"x":11.49,"y":11.54,"rotation":46.55,"width":39,"height":32}},"hand(right)":{"hand(right)":{"x":11.7,"y":-15.14,"rotation":126.47,"width":41,"height":36}},"head":{"head":{"x":27.47,"y":10.81,"rotation":-90,"width":90,"height":80}},"leg(left)":{"leg(left)":{"x":2.95,"y":-0.34,"rotation":95.04,"width":12,"height":15}},"leg(right)":{"leg(right)":{"x":2.95,"y":0.58,"rotation":94.9,"width":13,"height":15}},"magic circle(blue)":{"magic circle(blue)":{"x":-1.08,"y":-2.47,"width":93,"height":26}},"shadow":{"shadow":{"x":-0.31,"y":0.29,"rotation":91.36,"width":93,"height":30}}}}],"events":{"attack":{}},"animations":{"damage":{"slots":{"body":{"rgba":[{"color":"ffffffff"},{"time":0.1333,"color":"e58585ff","curve":"stepped"},{"time":0.3,"color":"e58585ff"},{"time":0.4,"color":"ffffffff"}]},"hand(left)":{"rgba":[{"time":0.1333,"color":"e58585ff"}]},"hand(right)":{"rgba":[{"time":0.1333,"color":"e58585ff"}]},"head":{"rgba":[{"color":"ffffffff"},{"time":0.1333,"color":"e58585ff","curve":"stepped"},{"time":0.3,"color":"e58585ff"},{"time":0.4,"color":"ffffffff"}]},"leg(left)":{"rgba":[{"color":"ffffffff"},{"time":0.1333,"color":"e58585ff","curve":"stepped"},{"time":0.3,"color":"e58585ff"},{"time":0.4,"color":"ffffffff"}]},"leg(right)":{"rgba":[{"color":"ffffffff"},{"time":0.1333,"color":"e58585ff","curve":"stepped"},{"time":0.3,"color":"e58585ff"},{"time":0.4,"color":"ffffffff"}]},"magic circle(blue)":{"rgba":[{"color":"ffffff00"}]},"shadow":{"rgba":[{"time":0.1333,"color":"ffffffa9"}]}},"bones":{"body":{"rotate":[{},{"time":0.1333,"value":8.25},{"time":0.3,"value":8.99},{"time":0.4}],"translate":[{},{"time":0.1333,"x":-1.15,"y":0.21},{"time":0.3,"x":-1.83,"y":-0.73},{"time":0.4}]},"bone":{"rotate":[{},{"time":0.1333,"value":6.25},{"time":0.3,"value":20.99},{"time":0.4}],"translate":[{},{"time":0.1333,"x":-23.76,"y":3.26},{"time":0.3,"x":-36.49,"y":1.76},{"time":0.4}]},"head":{"rotate":[{},{"time":0.1333,"value":1.4},{"time":0.3,"value":3.79},{"time":0.4}],"translate":[{},{"time":0.1333,"x":-0.84,"y":-2.8},{"time":0.3,"x":-1.25,"y":-3.29},{"time":0.4}]},"shadow":{"rotate":[{"curve":"stepped"},{"time":0.4}],"translate":[{},{"time":0.1333,"x":-16.44},{"time":0.3,"x":-28.29},{"time":0.4}],"scale":[{"curve":"stepped"},{"time":0.4}]}}},"death":{"slots":{"body":{"rgba":[{"color":"ffffffff"},{"time":0.4,"color":"ffffff00"}]},"hand(left)":{"rgba":[{"color":"ffffffff"},{"time":0.4,"color":"ffffff00"}]},"hand(right)":{"rgba":[{"color":"ffffffff"},{"time":0.4,"color":"ffffff00"}]},"head":{"rgba":[{"color":"ffffffff"},{"time":0.4,"color":"ffffff00"}]},"leg(left)":{"rgba":[{"color":"ffffffff"},{"time":0.4,"color":"ffffff00"}]},"leg(right)":{"rgba":[{"color":"ffffffff"},{"time":0.4,"color":"ffffff00"}]},"magic circle(blue)":{"rgba":[{"color":"ffffff00"}]},"shadow":{"rgba":[{"color":"ffffffff"},{"time":0.3333,"color":"ffffff00"}]}},"bones":{"body":{"rotate":[{},{"time":0.1333,"value":8.25},{"time":0.3,"value":8.99},{"time":0.4}],"translate":[{},{"time":0.1333,"x":-1.15,"y":0.21},{"time":0.3,"x":-1.83,"y":-0.73},{"time":0.4}]},"bone":{"rotate":[{},{"time":0.1,"value":11.92},{"time":0.2,"value":22.18},{"time":0.2667,"value":27.84}],"translate":[{},{"time":0.1,"x":-23.76},{"time":0.2,"x":-40.97,"y":7.05},{"time":0.2667,"x":-49.18,"y":7.05}]},"head":{"rotate":[{},{"time":0.1333,"value":1.4},{"time":0.3,"value":3.79},{"time":0.4}],"translate":[{},{"time":0.1333,"x":-0.84,"y":-2.8},{"time":0.3,"x":-1.25,"y":-3.29},{"time":0.4}]},"shadow":{"rotate":[{"curve":"stepped"},{"time":0.3333}],"translate":[{},{"time":0.1333,"x":-16.44},{"time":0.2333,"x":-28.29},{"time":0.3333,"x":-39.33}],"scale":[{"curve":"stepped"},{"time":0.3333}]}}},"explosion":{"slots":{"body":{"rgba":[{"color":"ffffffff"},{"time":0.3333,"color":"ffffff00"}]},"hand(left)":{"rgba":[{"color":"ffffffff"},{"time":0.2667,"color":"ffffff00"}]},"hand(right)":{"rgba":[{"color":"ffffffff"},{"time":0.2667,"color":"ffffff00"}]},"head":{"rgba":[{"color":"ffffffff"},{"time":0.2667,"color":"ffffff00"}]},"leg(left)":{"rgba":[{"color":"ffffffff"},{"time":0.2667,"color":"ffffff00"}]},"leg(right)":{"rgba":[{"color":"ffffffff"},{"time":0.2667,"color":"ffffff00"}]},"magic circle(blue)":{"rgba":[{"color":"ffffff00"}]},"shadow":{"rgba":[{"color":"ffffffff"},{"time":0.3333,"color":"ffffff00"}]}},"bones":{"body":{"rotate":[{},{"time":0.1,"value":8.25},{"time":0.2333,"value":8.99},{"time":0.3333}],"translate":[{},{"time":0.1,"x":-1.15,"y":0.21},{"time":0.2333,"x":-1.83,"y":-0.73},{"time":0.3333}]},"bone":{"rotate":[{},{"time":0.1,"value":-35.2},{"time":0.2,"value":-112.23},{"time":0.2667,"value":-140.93}],"translate":[{},{"time":0.1,"x":-3.86},{"time":0.2,"x":-2.39,"y":12.53},{"time":0.2667,"x":-0.92,"y":22.11}]},"head":{"rotate":[{},{"time":0.0667,"value":1.4},{"time":0.2,"value":3.79},{"time":0.2667}],"translate":[{},{"time":0.0667,"x":-0.84,"y":-2.8},{"time":0.2,"x":-1.25,"y":-3.29},{"time":0.2667}]},"shadow":{"rotate":[{"curve":"stepped"},{"time":0.3333}],"translate":[{},{"time":0.3333,"x":9.31}],"scale":[{"curve":"stepped"},{"time":0.3333}]}}},"idle":{"slots":{"magic circle(blue)":{"rgba":[{"color":"ffffff00"}]}},"bones":{"bone":{"translate":[{"curve":"stepped"},{"time":0.5}]},"head":{"translate":[{},{"time":0.1333,"x":1.2,"y":0.03},{"time":0.3667,"x":-1.39,"y":-0.03},{"time":0.5}]},"shadow":{"rotate":[{"curve":"stepped"},{"time":0.5}],"translate":[{"curve":"stepped"},{"time":0.5}],"scale":[{},{"time":0.2333,"x":0.983,"y":0.955},{"time":0.5}]},"body":{"translate":[{},{"time":0.1333,"x":1.16,"y":0.03},{"time":0.3667,"x":0.28,"y":0.01},{"time":0.5}]},"leg(left)":{"rotate":[{"curve":"stepped"},{"time":0.5}],"translate":[{},{"time":0.1333,"x":0.71},{"time":0.3667,"x":-0.92},{"time":0.5}]},"leg(right)":{"rotate":[{"curve":"stepped"},{"time":0.1333,"curve":"stepped"},{"time":0.5}],"translate":[{},{"time":0.1333,"x":-0.41},{"time":0.3333,"x":0.71},{"time":0.5}]},"hand(left)":{"rotate":[{},{"time":0.2667,"value":-4.01},{"time":0.5}],"translate":[{"curve":"stepped"},{"time":0.5}]},"hand(right)":{"rotate":[{},{"time":0.2333,"value":11.07},{"time":0.5}],"translate":[{"curve":"stepped"},{"time":0.5}]}}},"run":{"slots":{"magic circle(blue)":{"rgba":[{"color":"ffffff00"}]}},"bones":{"bone":{"translate":[{},{"time":0.1667,"y":3.76},{"time":0.3333}]},"head":{"translate":[{},{"time":0.1,"x":4.21,"y":0.1},{"time":0.2333,"x":-3.65,"y":-0.09},{"time":0.3333}]},"shadow":{"rotate":[{"curve":"stepped"},{"time":0.3333}],"translate":[{"curve":"stepped"},{"time":0.3333}],"scale":[{},{"time":0.1333,"x":0.983,"y":0.955},{"time":0.3333}]},"body":{"translate":[{},{"time":0.1,"x":1.92,"y":0.05},{"time":0.2667,"x":-1.23,"y":-0.03},{"time":0.3333}]},"leg(left)":{"rotate":[{"curve":"stepped"},{"time":0.3333}],"translate":[{},{"time":0.0667,"x":0.71},{"time":0.2667,"x":-0.92},{"time":0.3333}]},"leg(right)":{"rotate":[{"curve":"stepped"},{"time":0.0667,"curve":"stepped"},{"time":0.3333}],"translate":[{},{"time":0.0667,"x":-0.41},{"time":0.2333,"x":0.71},{"time":0.3333}]},"hand(left)":{"rotate":[{},{"time":0.1667,"value":14.85},{"time":0.3333}],"translate":[{"curve":"stepped"},{"time":0.3333}]},"hand(right)":{"rotate":[{},{"time":0.2,"value":-15.03},{"time":0.3333}],"translate":[{"curve":"stepped"},{"time":0.3333}]}}},"skill":{"slots":{"magic circle(blue)":{"rgba":[{"color":"ffffff00"},{"time":0.1667,"color":"ffffffff"},{"time":0.3333,"color":"ffffff00"},{"time":0.5,"color":"ffffffff"},{"time":0.6667,"color":"ffffff00"},{"time":0.8333,"color":"ffffffff"},{"time":1,"color":"ffffff00"}]},"shadow":{"rgba":[{"color":"ffffffff"},{"time":0.4333,"color":"ffffff8b"},{"time":0.6667,"color":"ffffff60"},{"time":1,"color":"ffffffdf"}]}},"bones":{"bone":{"rotate":[{"curve":"stepped"},{"time":0.3333}],"translate":[{"curve":"stepped"},{"time":0.3333},{"time":0.5,"y":-4.95,"curve":[0.558,0,0.675,0.59,0.558,-4.95,0.675,11.74]},{"time":0.7333,"x":0.59,"y":11.74,"curve":[0.759,0.59,0.795,0.5,0.759,11.74,0.795,11.56]},{"time":0.8333,"x":0.39,"y":11.33,"curve":[0.893,0.22,0.959,0,0.893,6.48,0.959,0]},{"time":1}]},"head":{"rotate":[{},{"time":0.8,"value":3.69},{"time":1}],"translate":[{},{"time":0.1667,"x":1.2,"y":0.03},{"time":0.3333,"x":-0.99,"y":-0.02},{"time":0.5,"x":2.25,"y":0.05},{"time":0.6667,"x":-6.46,"y":-0.15},{"time":0.8,"x":-11.59,"y":-0.28},{"time":1}]},"shadow":{"rotate":[{"curve":"stepped"},{"time":0.4333,"curve":"stepped"},{"time":1}],"translate":[{"curve":"stepped"},{"time":0.4333,"curve":"stepped"},{"time":1}],"scale":[{"curve":"stepped"},{"time":0.4333},{"time":0.6667,"x":0.983,"y":0.933},{"time":1}]},"body":{"translate":[{},{"time":0.3333,"x":0.28,"y":0.01},{"time":0.5,"x":1.16,"y":0.03},{"time":0.8,"x":-11.03,"y":-0.26},{"time":1}]},"magic circle":{"rotate":[{"curve":"stepped"},{"time":0.5,"curve":"stepped"},{"time":1}],"translate":[{"curve":"stepped"},{"time":0.5,"curve":"stepped"},{"time":1}],"scale":[{"x":0.859,"y":0.905},{"time":0.5,"curve":"stepped"},{"time":1}]},"leg(left)":{"rotate":[{"curve":"stepped"},{"time":0.3333,"curve":"stepped"},{"time":1}],"translate":[{"curve":"stepped"},{"time":0.3333},{"time":0.5,"x":-2.12},{"time":0.6667,"x":-0.71},{"time":0.8333,"x":-2.47},{"time":1}]},"leg(right)":{"rotate":[{"curve":"stepped"},{"time":0.3333,"curve":"stepped"},{"time":1}],"translate":[{"curve":"stepped"},{"time":0.3333},{"time":0.5,"x":-1.41},{"time":0.6667,"x":0.47},{"time":0.8333,"x":-1.89},{"time":1}]}}}}}