{"skeleton":{"hash":"GlsIn2b+O4M","spine":"4.0.39","x":-29,"y":-30.5,"width":58,"height":61,"images":"","audio":""},"bones":[{"name":"root"}],"slots":[{"name":"img","bone":"root","attachment":"img"}],"skins":[{"name":"default","attachments":{"img":{"img":{"width":58,"height":61}}}}],"animations":{"hide":{"slots":{"img":{"rgba":[{"color":"ffffffff"},{"time":0.1667,"color":"ffffff00"}]}}},"normal":{"bones":{"root":{"rotate":[{},{"time":0.1,"value":-90},{"time":0.2,"value":-180},{"time":0.3,"value":-270},{"time":0.4,"value":-360}]}}},"show":{"slots":{"img":{"rgba":[{"color":"ffffff00"},{"time":0.1667,"color":"ffffffff"}]}}}}}